hurodes/__init__.py
hurodes/humanoid_robot.py
hurodes/generators/__init__.py
hurodes/generators/generator_base.py
hurodes/generators/hrdf_mixin.py
hurodes/generators/mjcf_generator/__init__.py
hurodes/generators/mjcf_generator/mjcf_generator_base.py
hurodes/generators/mjcf_generator/mjcf_generator_composite.py
hurodes/generators/mjcf_generator/mjcf_humanoid_generator.py
hurodes/generators/mjcf_generator/scene_constants.py
hurodes/generators/urdf_generator/__init__.py
hurodes/generators/urdf_generator/urdf_generator_base.py
hurodes/generators/urdf_generator/urdf_humanoid_generator.py
hurodes/hrdf/__init__.py
hurodes/hrdf/hrdf.py
hurodes/hrdf/base/__init__.py
hurodes/hrdf/base/attribute.py
hurodes/hrdf/base/info.py
hurodes/hrdf/infos/__init__.py
hurodes/hrdf/infos/actuator.py
hurodes/hrdf/infos/body.py
hurodes/hrdf/infos/joint.py
hurodes/hrdf/infos/mesh.py
hurodes/hrdf/infos/simple_geom.py
hurodes/joint_mapping/__init__.py
hurodes/joint_mapping/base_solver.py
hurodes/joint_mapping/casadi_uitl.py
hurodes/joint_mapping/double_link_solver.py
hurodes/joint_mapping/joint_mapping_config.py
hurodes/joint_mapping/numba_util.py
hurodes/parsers/__init__.py
hurodes/parsers/base_parser.py
hurodes/parsers/mjcf_parser.py
hurodes/parsers/urdf_mujoco_parser.py
hurodes/parsers/urdf_original_parser.py
hurodes/scripts/__init__.py
hurodes/scripts/generate.py
hurodes/scripts/generate_composite.py
hurodes/scripts/parse.py
hurodes/utils/__init__.py
hurodes/utils/config.py
hurodes/utils/convert.py
hurodes/utils/mesh.py
hurodes/utils/string.py
hurodes/utils/xml.py
hurodes-0.1.9.dist-info/METADATA
hurodes-0.1.9.dist-info/WHEEL
hurodes-0.1.9.dist-info/entry_points.txt
hurodes-0.1.9.dist-info/top_level.txt
hurodes-0.1.9.dist-info/RECORD
