Metadata-Version: 2.4
Name: hurodes
Version: 0.1.9
Summary: hurodes (Humanoid Robot Description) is a Python toolkit for describing, converting, and processing humanoid robot models.
Home-page: https://github.com/ZyuonRobotics/humanoid-robot-description
Author: ZyuonRobotics
Maintainer: Honglong Tian
License: MIT
Keywords: robotics,humanoid,urdf,mujoco
Classifier: Development Status :: 3 - Alpha
Classifier: Intended Audience :: Developers
Classifier: License :: OSI Approved :: MIT License
Classifier: Programming Language :: Python :: 3
Classifier: Programming Language :: Python :: 3.9
Classifier: Programming Language :: Python :: 3.10
Classifier: Programming Language :: Python :: 3.11
Classifier: Programming Language :: Python :: 3.12
Classifier: Topic :: Software Development :: Libraries :: Python Modules
Requires-Python: >=3.9
Requires-Dist: pandas>=2.0
Requires-Dist: numpy>=1.22.4
Requires-Dist: colorama>=0.4.6
Requires-Dist: click>=8.0
Requires-Dist: tqdm>=4.67.1
Requires-Dist: bidict
Requires-Dist: PyYAML>=6.0
Requires-Dist: pydantic>=2.0
Requires-Dist: mujoco>=3.3.0
Requires-Dist: scipy>=1.10.0
Provides-Extra: dev
Requires-Dist: setuptools==68.2.2; extra == "dev"
Requires-Dist: wheel==0.43.0; extra == "dev"
Requires-Dist: pytest; extra == "dev"
Requires-Dist: build; extra == "dev"
Requires-Dist: twine; extra == "dev"
Provides-Extra: mesh
Requires-Dist: trimesh>=4.5.10; extra == "mesh"
Requires-Dist: fast-simplification>=0.1.11; extra == "mesh"
Provides-Extra: hal
Requires-Dist: casadi>=3.5.0; extra == "hal"
Requires-Dist: numba>=0.57.0; extra == "hal"
Provides-Extra: all
Requires-Dist: trimesh>=4.5.10; extra == "all"
Requires-Dist: fast-simplification>=0.1.11; extra == "all"
Requires-Dist: casadi>=3.5.0; extra == "all"
Requires-Dist: numba>=0.57.0; extra == "all"
Dynamic: author
Dynamic: classifier
Dynamic: description
Dynamic: description-content-type
Dynamic: home-page
Dynamic: keywords
Dynamic: license
Dynamic: maintainer
Dynamic: provides-extra
Dynamic: requires-dist
Dynamic: requires-python
Dynamic: summary
